<?xml version="1.0" encoding="UTF-8" ?>
<bmtcustomdata><namespace name="visuals"><object name="[ATGDW].[ARF_TIME_HOUR]"><property name="position">point:205,535</property><property name="state">long:2</property><property name="size">size:-1,1</property></object><object name="[ATGDW].[ARF_TIME_TOD]"><property name="position">point:32,1704</property><property name="state">long:2</property><property name="size">size:-1,1</property></object><object name="[ATGDW].[ARF_CAL_QOY]"><property name="position">point:572,718</property><property name="state">long:2</property><property name="size">size:-1,1</property></object><object name="[ATGDW].[ARF_CAL_MOY]"><property name="position">point:398,839</property><property name="state">long:2</property><property name="size">size:-1,1</property></object><object name="[ATGDW].[ARF_CAL_DOW]"><property name="position">point:205,889</property><property name="state">long:2</property><property name="size">size:-1,1</property></object><object name="[ATGDW].[ARF_USER]"><property name="position">point:398,1415</property><property name="state">long:2</property><property name="size">size:-1,1</property></object><object name="[ATGDW].[ARF_GENDER]"><property name="position">point:179,1503</property><property name="state">long:2</property><property name="size">size:-1,1</property></object><object name="[ATGDW].[ARF_LANGUAGE]"><property name="position">point:581,1471</property><property name="state">long:2</property><property name="size">size:-1,1</property></object><object name="[ATGDW].[ARF_CURRENCY]"><property name="position">point:206,1697</property><property name="state">long:2</property><property name="size">size:-1,1</property></object><object name="[ATGDW].[ARF_GEO_REGION]"><property name="position">point:234,1238</property><property name="state">long:2</property><property name="size">size:-1,1</property></object><object name="[ATGDW].[ARF_GEO_COUNTRY]"><property name="position">point:426,1231</property><property name="state">long:2</property><property name="size">size:-1,1</property></object><object name="[ATGDW].[ARF_AGE_GROUP]"><property name="position">point:234,1003</property><property name="state">long:2</property><property name="size">size:-1,1</property></object><object name="[ATGDW].[ARF_MARITAL_STATUS]"><property name="position">point:234,1131</property><property name="state">long:2</property><property name="size">size:-1,1</property></object><object name="[ATGDW].[ARF_DEMOGRAPHIC]"><property name="position">point:32,1237</property><property name="state">long:2</property><property name="size">size:-1,1</property></object><object name="[ATGDW].[ARF_SEGCLSTR]"><property name="position">point:341,0</property><property name="state">long:2</property><property name="size">size:-1,1</property></object><object name="[ATGDW].[ARF_SEGCLSTR_MBRS]"><property name="position">point:38,146</property><property name="state">long:2</property><property name="size">size:-1,1</property></object><object name="[ATGDW].[ARF_SEGMENT]"><property name="position">point:387,155</property><property name="state">long:2</property><property name="size">size:-1,1</property></object><object name="[ATGDW].[ARF_STIMGRP]"><property name="position">point:241,207</property><property name="state">long:2</property><property name="size">size:-1,1</property></object><object name="[ATGDW].[ARF_STIMGRP_MBRS]"><property name="position">point:32,271</property><property name="state">long:2</property><property name="size">size:-1,1</property></object><object name="[ATGDW].[ARF_STIMULUS]"><property name="position">point:241,307</property><property name="state">long:2</property><property name="size">size:-1,1</property></object><object name="[ATGDW].[ARF_SITE_VISIT]"><property name="position">point:389,1683</property><property name="state">long:2</property><property name="size">size:-1,1</property></object><object name="[ATGDW].[ARF_SKU]"><property name="position">point:32,2</property><property name="state">long:2</property><property name="size">size:-1,1</property></object><object name="[Returns].[Return Item Measures]"><property name="position">point:320,342</property><property name="state">long:4</property><property name="size">size:140,72</property></object><object name="[Returns].[Return]"><property name="position">point:612,421</property><property name="state">long:4</property><property name="size">size:100,90</property></object><object name="[Sales].[Geography]"><property name="position">point:444,48</property><property name="state">long:4</property><property name="size">size:100,90</property></object><object name="[Sales].[Geography (Billing)]"><property name="position">point:212,157</property><property name="state">long:4</property><property name="size">size:133,90</property></object><object name="[Sales].[Geography (Shipping)]"><property name="position">point:308,86</property><property name="state">long:4</property><property name="size">size:140,90</property></object><object name="[Sales].[Origin Sales Channel]"><property name="position">point:830,265</property><property name="state">long:4</property><property name="size">size:140,72</property></object><object name="[Sales].[Submit Sales Channel]"><property name="position">point:868,381</property><property name="state">long:4</property><property name="size">size:140,72</property></object><object name="[Sales].[Agent]"><property name="position">point:564,48</property><property name="state">long:4</property><property name="size">size:100,90</property></object><object name="[Sales].[Time Interval]"><property name="position">point:779,166</property><property name="state">long:4</property><property name="size">size:100,72</property></object><object name="[Sales]"><property name="position">point:103,55</property><property name="state">long:33</property><property name="size">size:34,60</property><property name="appState">long:0</property><property name="offset">point:-16,-16</property><property name="scrollPosX">long:0</property><property name="scrollPosY">long:0</property><property name="zoom">double:1.000000</property><property name="layoutType">long:4102</property><property name="parentDist">long:0</property><property name="borderSize">long:1</property><property name="root">string:</property></object><object name="[Sales].[Catalog]"><property name="position">point:680,769</property><property name="state">long:4</property><property name="size">size:100,108</property></object><object name="[Sales].[Search Term]"><property name="position">point:680,86</property><property name="state">long:4</property><property name="size">size:100,90</property></object><object name="[Sales].[Customer]"><property name="position">point:564,825</property><property name="state">long:4</property><property name="size">size:100,72</property></object><object name="[Sales].[Stimulus]"><property name="position">point:394,816</property><property name="state">long:4</property><property name="size">size:200,90</property></object><object name="[Sales].[Segment]"><property name="position">point:278,778</property><property name="state">long:4</property><property name="size">size:200,90</property></object><object name="[Sales].[Promotion]"><property name="position">point:179,707</property><property name="state">long:4</property><property name="size">size:200,90</property></object><object name="[Sales].[Local Currency]"><property name="position">point:158,617</property><property name="state">long:4</property><property name="size">size:100,72</property></object><object name="[Sales].[Gender]"><property name="position">point:120,501</property><property name="state">long:4</property><property name="size">size:100,72</property></object><object name="[Sales].[Age Group]"><property name="position">point:120,381</property><property name="state">long:4</property><property name="size">size:100,72</property></object><object name="[Sales].[Marital Status]"><property name="position">point:158,265</property><property name="state">long:4</property><property name="size">size:100,72</property></object><object name="[Commerce (Model)]"><property name="position">point:72,165</property><property name="state">long:16</property><property name="size">size:2561,4160</property><property name="appState">long:0</property><property name="offset">point:-32,-32</property><property name="scrollPosX">long:320</property><property name="scrollPosY">long:1404</property><property name="zoom">double:0.500000</property><property name="layoutType">long:4102</property><property name="parentDist">long:0</property><property name="borderSize">long:1</property><property name="root">string:</property><property name="color">long:15122624</property></object><object name="[Model View]"><property name="position">point:214,124</property><property name="state">long:32</property><property name="size">size:63,60</property><property name="appState">long:0</property><property name="offset">point:-48,-48</property><property name="scrollPosX">long:90</property><property name="scrollPosY">long:2799</property><property name="zoom">double:1.000000</property><property name="layoutType">long:4102</property><property name="parentDist">long:0</property><property name="borderSize">long:1</property><property name="root">string:</property></object><object name="[Site Visits].[Site Visit Measures]"><property name="position">point:339,288</property><property name="state">long:4</property><property name="size">size:133,72</property></object><object name="[Site Visits].[Site Visit]"><property name="position">point:585,205</property><property name="state">long:4</property><property name="size">size:100,72</property></object><object name="[Site Visits]"><property name="position">point:0,55</property><property name="state">long:0</property><property name="size">size:53,60</property><property name="appState">long:0</property><property name="offset">point:-16,-16</property><property name="scrollPosX">long:0</property><property name="scrollPosY">long:0</property><property name="zoom">double:1.000000</property><property name="layoutType">long:4102</property><property name="parentDist">long:0</property><property name="borderSize">long:1</property><property name="root">string:</property></object><object name="[Sales].[Line Item Measures]"><property name="position">point:491,432</property><property name="state">long:4</property><property name="size">size:126,90</property></object><object name="[Sales].[Order]"><property name="position">point:779,707</property><property name="state">long:4</property><property name="size">size:100,90</property></object><object name="[Sales].[Date]"><property name="position">point:788,474</property><property name="state">long:4</property><property name="size">size:300,126</property></object><object name="[Sales].[Time]"><property name="position">point:850,608</property><property name="state">long:4</property><property name="size">size:100,90</property></object><object name="[Site Visits].[Date]"><property name="position">point:485,344</property><property name="state">long:4</property><property name="size">size:300,126</property></object><object name="[Site Visits].[Time]"><property name="position">point:478,490</property><property name="state">long:4</property><property name="size">size:100,90</property></object><object name="[Site Visits].[Visitor]"><property name="position">point:170,132</property><property name="state">long:4</property><property name="size">size:100,72</property></object><object name="[Site Visits].[Gender]"><property name="position">point:314,528</property><property name="state">long:4</property><property name="size">size:100,72</property></object><object name="[Site Visits].[Geography]"><property name="position">point:170,435</property><property name="state">long:4</property><property name="size">size:100,90</property></object><object name="[Site Visits].[Age Group]"><property name="position">point:314,48</property><property name="state">long:4</property><property name="size">size:100,72</property></object><object name="[Site Visits].[Marital Status]"><property name="position">point:477,77</property><property name="state">long:4</property><property name="size">size:100,72</property></object><object name="[Site Visits].[Stimulus]"><property name="position">point:63,279</property><property name="state">long:4</property><property name="size">size:200,90</property></object><object name="[Sales Facts].[Segment Cluster]"><property name="position">point:792,944</property><property name="state">long:2</property><property name="size">size:-1,1</property></object><object name="[Sales Facts].[Promotion Group]"><property name="position">point:775,1082</property><property name="state">long:2</property><property name="size">size:-1,1</property></object><object name="[Sales Facts].[Local Currency]"><property name="position">point:1105,1357</property><property name="state">long:2</property><property name="size">size:-1,1</property></object><object name="[Sales Facts].[Demographic]"><property name="position">point:938,630</property><property name="state">long:2</property><property name="size">size:-1,1</property></object><object name="[Sales Facts].[Gender]"><property name="position">point:539,420</property><property name="state">long:2</property><property name="size">size:-1,1</property></object><object name="[Sales Facts].[Age Group]"><property name="position">point:740,230</property><property name="state">long:2</property><property name="size">size:-1,1</property></object><object name="[Sales Facts].[Marital Status]"><property name="position">point:989,117</property><property name="state">long:2</property><property name="size">size:-1,1</property></object><object name="[Sales Facts].[Region]"><property name="position">point:406,667</property><property name="state">long:2</property><property name="size">size:-1,1</property></object><object name="[Sales Facts].[Country]"><property name="position">point:0,529</property><property name="state">long:2</property><property name="size">size:-1,1</property></object><object name="[Sales Facts].[Billing Region]"><property name="position">point:980,1301</property><property name="state">long:2</property><property name="size">size:-1,1</property></object><object name="[Sales Facts].[Billing Country]"><property name="position">point:744,1658</property><property name="state">long:2</property><property name="size">size:-1,1</property></object><object name="[Sales Facts].[Shipping Region]"><property name="position">point:877,1206</property><property name="state">long:2</property><property name="size">size:-1,1</property></object><object name="[Sales Facts].[Shipping Country]"><property name="position">point:538,1468</property><property name="state">long:2</property><property name="size">size:-1,1</property></object><object name="[Sales Facts].[Origin Sales Channel]"><property name="position">point:1324,553</property><property name="state">long:2</property><property name="size">size:-1,1</property></object><object name="[Sales Facts].[Submit Sales Channel]"><property name="position">point:1439,630</property><property name="state">long:2</property><property name="size">size:-1,1</property></object><object name="[Sales Facts].[Agent]"><property name="position">point:1613,741</property><property name="state">long:2</property><property name="size">size:-1,1</property></object><object name="[Sales Facts].[Agent Organization]"><property name="position">point:1961,538</property><property name="state">long:2</property><property name="size">size:-1,1</property></object><object name="[Sales Facts].[Time Interval]"><property name="position">point:1917,1001</property><property name="state">long:4098</property><property name="size">size:-1,-1</property></object><object name="[Sales Facts]"><property name="position">point:56,1434</property><property name="state">long:16</property><property name="size">size:2457,2678</property><property name="appState">long:1</property><property name="offset">point:-16,-16</property><property name="scrollPosX">long:656</property><property name="scrollPosY">long:349</property><property name="zoom">double:0.632603</property><property name="layoutType">long:4102</property><property name="parentDist">long:0</property><property name="borderSize">long:1</property><property name="root">string:[Sales Facts].[Line Item Facts]</property><property name="color">long:15790272</property></object><object name="[Return Facts].[Return Item Facts]"><property name="position">point:260,479</property><property name="state">long:2</property><property name="size">size:-1,1</property></object><object name="[Return Facts].[Return Date]"><property name="position">point:432,545</property><property name="state">long:2</property><property name="size">size:-1,1</property></object><object name="[Return Facts].[Return Time]"><property name="position">point:344,638</property><property name="state">long:2</property><property name="size">size:-1,1</property></object><object name="[Return Facts].[Category]"><property name="position">point:428,0</property><property name="state">long:2</property><property name="size">size:-1,1</property></object><object name="[Return Facts].[Product]"><property name="position">point:364,160</property><property name="state">long:2</property><property name="size">size:-1,1</property></object><object name="[Return Facts].[Sku]"><property name="position">point:307,320</property><property name="state">long:2</property><property name="size">size:-1,1</property></object><object name="[Return Facts].[Customer]"><property name="position">point:179,638</property><property name="state">long:2</property><property name="size">size:-1,1</property></object><object name="[Return Facts].[Local Currency]"><property name="position">point:99,545</property><property name="state">long:2</property><property name="size">size:-1,1</property></object><object name="[Return Facts].[Return Reason]"><property name="position">point:56,413</property><property name="state">long:2</property><property name="size">size:-1,1</property></object><object name="[Return Facts].[Return Sales Channel]"><property name="position">point:133,320</property><property name="state">long:2</property><property name="size">size:-1,1</property></object><object name="[Return Facts].[Agent]"><property name="position">point:446,413</property><property name="state">long:2</property><property name="size">size:-1,1</property></object><object name="[Return Facts].[Agent Organization]"><property name="position">point:578,347</property><property name="state">long:2</property><property name="size">size:-1,1</property></object><object name="[Return Facts].[Time Interval]"><property name="position">point:576,643</property><property name="state">long:4098</property><property name="size">size:-1,1</property></object><object name="[Return Facts]"><property name="appState">long:1</property><property name="offset">point:-16,-16</property><property name="scrollPosX">long:0</property><property name="scrollPosY">long:74</property><property name="zoom">double:1.000000</property><property name="layoutType">long:4102</property><property name="parentDist">long:0</property><property name="borderSize">long:1</property><property name="root">string:</property></object><object name="[Returns].[Return Date]"><property name="position">point:408,546</property><property name="state">long:4</property><property name="size">size:300,126</property></object><object name="[Returns].[Return Time]"><property name="position">point:340,618</property><property name="state">long:4</property><property name="size">size:100,90</property></object><object name="[Returns].[Catalog]"><property name="position">point:172,555</property><property name="state">long:4</property><property name="size">size:100,108</property></object><object name="[Returns].[Customer]"><property name="position">point:68,430</property><property name="state">long:4</property><property name="size">size:100,72</property></object><object name="[Returns].[Local Currency]"><property name="position">point:68,254</property><property name="state">long:4</property><property name="size">size:100,72</property></object><object name="[Returns].[Return Reason]"><property name="position">point:612,254</property><property name="state">long:4</property><property name="size">size:100,72</property></object><object name="[Returns].[Return Sales Channel]"><property name="position">point:488,111</property><property name="state">long:4</property><property name="size">size:140,72</property></object><object name="[Returns].[Agent]"><property name="position">point:172,102</property><property name="state">long:4</property><property name="size">size:100,90</property></object><object name="[Returns].[Time Interval]"><property name="position">point:340,57</property><property name="state">long:4</property><property name="size">size:100,72</property></object><object name="[ATGDW].[ARF_PRODUCT]"><property name="position">point:32,2</property><property name="state">long:2</property><property name="size">size:-1,1</property></object><object name="[ATGDW].[ARF_CATEGORY]"><property name="position">point:32,2</property><property name="state">long:2</property><property name="size">size:-1,1</property></object><object name="[ATGDW].[ARF_PROMOGRP]"><property name="position">point:32,2</property><property name="state">long:2</property><property name="size">size:-1,1</property></object><object name="[ATGDW].[ARF_PROMOTION]"><property name="position">point:32,2</property><property name="state">long:2</property><property name="size">size:-1,1</property></object><object name="[ATGDW].[ARF_PROMOGRP_MBRS]"><property name="position">point:32,2</property><property name="state">long:2</property><property name="size">size:-1,1</property></object><object name="[ATGDW].[ARF_LINE_ITEM]"><property name="position">point:32,2</property><property name="state">long:2</property><property name="size">size:-1,1</property></object><object name="[ATGDW].[ARF_TIME_DAY]"><property name="position">point:32,627</property><property name="state">long:2</property><property name="size">size:-1,1</property></object><object name="[ATGDW].[ARF_TIME_MONTH]"><property name="position">point:205,711</property><property name="state">long:2</property><property name="size">size:-1,1</property></object><object name="[ATGDW].[ARF_TIME_QTR]"><property name="position">point:398,711</property><property name="state">long:2</property><property name="size">size:-1,1</property></object><object name="[ATGDW].[ARF_TIME_YEAR]"><property name="state">long:2</property><property name="size">size:-1,1</property></object><object name="[ATGDW].[ARF_TIME_WEEK]"><property name="position">point:205,421</property><property name="state">long:2</property><property name="size">size:-1,1</property></object><object name="[ATGDW]"><property name="position">point:0,52</property><property name="state">long:32</property><property name="size">size:49,60</property><property name="appState">long:1</property><property name="offset">point:-16,-16</property><property name="scrollPosX">long:0</property><property name="scrollPosY">long:0</property><property name="zoom">double:1.000000</property><property name="layoutType">long:2</property><property name="parentDist">long:30</property><property name="borderSize">long:20</property><property name="root">string:</property></object><object name="[Database View]"><property name="position">point:32,98</property><property name="state">long:16</property><property name="size">size:164,176</property><property name="appState">long:0</property><property name="offset">point:-32,-32</property><property name="scrollPosX">long:0</property><property name="scrollPosY">long:0</property><property name="zoom">double:1.000000</property><property name="layoutType">long:2</property><property name="parentDist">long:30</property><property name="borderSize">long:20</property><property name="root">string:</property><property name="color">long:12632294</property></object><object name="[Site Visit Facts].[Site Visit Facts]"><property name="position">point:891,591</property><property name="state">long:2</property><property name="size">size:-1,1</property></object><object name="[Site Visit Facts].[Site Visit]"><property name="position">point:642,630</property><property name="state">long:2</property><property name="size">size:-1,1</property></object><object name="[Site Visit Facts].[Date]"><property name="position">point:1187,614</property><property name="state">long:2</property><property name="size">size:-1,-1</property></object><object name="[Site Visit Facts].[Time]"><property name="position">point:1025,905</property><property name="state">long:2</property><property name="size">size:-1,1</property></object><object name="[Site Visit Facts].[Visitor]"><property name="position">point:745,786</property><property name="state">long:2</property><property name="size">size:-1,1</property></object><object name="[Site Visit Facts].[Demographic]"><property name="position">point:673,395</property><property name="state">long:2</property><property name="size">size:-1,1</property></object><object name="[Site Visit Facts].[Gender]"><property name="position">point:295,390</property><property name="state">long:2</property><property name="size">size:-1,1</property></object><object name="[Site Visit Facts].[Region]"><property name="position">point:296,855</property><property name="state">long:2</property><property name="size">size:-1,1</property></object><object name="[Site Visit Facts].[Country]"><property name="position">point:0,970</property><property name="state">long:2</property><property name="size">size:-1,1</property></object><object name="[Site Visit Facts].[Age Group]"><property name="position">point:634,32</property><property name="state">long:2</property><property name="size">size:-1,1</property></object><object name="[Site Visit Facts].[Marital Status]"><property name="position">point:1111,46</property><property name="state">long:2</property><property name="size">size:-1,1</property></object><object name="[Site Visit Facts].[Stimulus Group]"><property name="position">point:1184,477</property><property name="state">long:2</property><property name="size">size:-1,1</property></object><object name="[Site Visit Facts].[Time Interval]"><property name="position">point:1343,684</property><property name="state">long:4098</property><property name="size">size:-1,-1</property></object><object name="[Site Visit Facts]"><property name="position">point:56,61</property><property name="state">long:16</property><property name="size">size:1290,1353</property><property name="appState">long:1</property><property name="offset">point:-16,-16</property><property name="scrollPosX">long:760</property><property name="scrollPosY">long:401</property><property name="zoom">double:1.000000</property><property name="layoutType">long:4102</property><property name="parentDist">long:0</property><property name="borderSize">long:1</property><property name="root">string:</property><property name="color">long:15122624</property></object><object name="[Sales Facts].[Line Item Facts]"><property name="position">point:1216,776</property><property name="state">long:2</property><property name="size">size:-1,1</property></object><object name="[Sales Facts].[Line Item]"><property name="position">point:1269,519</property><property name="state">long:2</property><property name="size">size:-1,1</property></object><object name="[Sales Facts].[Order]"><property name="position">point:1318,93</property><property name="state">long:2</property><property name="size">size:-1,1</property></object><object name="[Sales Facts].[Date]"><property name="position">point:1645,1014</property><property name="state">long:2</property><property name="size">size:-1,1</property></object><object name="[Sales Facts].[Time]"><property name="position">point:1609,1147</property><property name="state">long:2</property><property name="size">size:-1,1</property></object><object name="[Sales Facts].[Category]"><property name="position">point:2048,1886</property><property name="state">long:2</property><property name="size">size:-1,1</property></object><object name="[Sales Facts].[Product]"><property name="position">point:1761,1572</property><property name="state">long:2</property><property name="size">size:-1,1</property></object><object name="[Sales Facts].[Sku]"><property name="position">point:1481,1258</property><property name="state">long:2</property><property name="size">size:-1,1</property></object><object name="[Sales Facts].[Search Term]"><property name="position">point:1649,874</property><property name="state">long:2</property><property name="size">size:-1,1</property></object><object name="[Sales Facts].[Customer]"><property name="position">point:1367,1335</property><property name="state">long:2</property><property name="size">size:-1,1</property></object><object name="[Sales Facts].[Stimulus Group]"><property name="position">point:1256,1369</property><property name="state">long:2</property><property name="size">size:-1,1</property></object><object name="[Returns]"><property name="position">point:187,55</property><property name="state">long:0</property><property name="size">size:45,60</property><property name="appState">long:0</property><property name="offset">point:-16,-16</property><property name="scrollPosX">long:0</property><property name="scrollPosY">long:0</property><property name="zoom">double:1.000000</property><property name="layoutType">long:4102</property><property name="parentDist">long:0</property><property name="borderSize">long:1</property><property name="root">string:</property></object><object name="[Commerce].[Time Interval]"><property name="position">point:282,49</property><property name="state">long:4</property><property name="size">size:100,72</property></object><object name="[Commerce]"><property name="position">point:109,48</property><property name="state">long:33</property><property name="size">size:57,60</property><property name="appState">long:0</property><property name="offset">point:-32,-32</property><property name="scrollPosX">long:0</property><property name="scrollPosY">long:0</property><property name="zoom">double:1.000000</property><property name="layoutType">long:2</property><property name="parentDist">long:30</property><property name="borderSize">long:20</property><property name="root">string:</property></object><object name="[Dimensional View]"><property name="position">point:327,124</property><property name="state">long:33</property><property name="size">size:91,60</property><property name="appState">long:0</property><property name="offset">point:-32,-32</property><property name="scrollPosX">long:0</property><property name="scrollPosY">long:0</property><property name="zoom">double:1.020000</property><property name="layoutType">long:4102</property><property name="parentDist">long:0</property><property name="borderSize">long:22</property><property name="root">string:</property></object><object name="[ATG]"><property name="appState">long:0</property><property name="offset">point:-48,-48</property><property name="scrollPosX">long:0</property><property name="scrollPosY">long:0</property><property name="zoom">double:1.000000</property><property name="layoutType">long:2</property><property name="parentDist">long:30</property><property name="borderSize">long:20</property><property name="root">string:</property></object><object name="[]"><property name="viewStyle">long:2</property><property name="lod">long:32</property><property name="lfWeight">long:0</property><property name="lfItalic">long:0</property><property name="lfStrikeOut">long:0</property><property name="lfUnderline">long:0</property><property name="lfCharSet">long:0</property><property name="lfFaceName">string:MS Shell Dlg</property><property name="textColor">long:-1</property><property name="BMTFW_Layout_Version">long:30</property><property name="BMTFW_Layout"><![CDATA[string:[Promotions].[Local Currency]
	dx=150,93
	parent=Promotions
	x=9,999
[Promotions].[Gender]
	dx=103,93
	parent=Promotions
	x=574,580
[Promotions].[Age Group]
	dx=123,93
	parent=Promotions
	x=556,790
[Promotions].[Marital Status]
	dx=141,93
	parent=Promotions
	x=538,886
[Promotions].[Geography]
	dx=125,113
	parent=Promotions
	x=554,981
[Promotions].[Geography (Billing)]
	dx=174,113
	parent=Promotions
	x=10,1095
[Promotions].[Origin Sales Channel]
	dx=184,93
	parent=Promotions
	x=186,1116
[Promotions].[Submit Sales Channel]
	dx=190,93
	parent=Promotions
	x=367,1116
[Promotions].[Agent]
	dx=125,113
	parent=Promotions
	x=555,1097
[Promotions].[Time Interval]
	dx=136,93
	parent=Promotions
	x=423,483
[Promotions].[Submitted Site]
	dx=192,93
	parent=Promotions
	x=279,44
[Promotions]
	c=99b2c7
	dx=200,28
	expanded=f
	parent=Commerce
	view=0,0
	x=11,1722
	zoom=1.000000
[Returns].[Return Item Measures]
	dx=189,89
	parent=Returns
	x=761,497
[Returns].[Return]
	dx=145,113
	parent=Returns
	x=604,237
[Returns].[Return Date]
	dx=300,153
	parent=Returns
	x=604,57
[Returns].[Return Time]
	dx=132,113
	parent=Returns
	x=789,237
[Returns].[Catalog]
	dx=160,133
	parent=Returns
	x=944,57
[Returns].[Customer]
	dx=139,113
	parent=Returns
	x=941,319
[Returns].[Local Currency]
	dx=150,93
	parent=Returns
	x=604,377
[Returns].[Return Reason]
	dx=147,93
	parent=Returns
	x=794,377
[Returns].[Return Sales Channel]
	dx=187,93
	parent=Returns
	x=1144,57
[Returns].[Agent]
	dx=125,113
	parent=Returns
	x=961,237
[Returns].[Time Interval]
	dx=136,93
	parent=Returns
	x=981,377
[Returns].[Item Site]
	dx=139,93
	parent=Returns
	x=11,1227
[Sales].[Age Group]
	dx=123,93
	parent=Sales
	x=10,817
[Sales].[Marital Status]
	dx=141,93
	parent=Sales
	x=200,677
[Sales].[Geography]
	dx=125,113
	parent=Sales
	x=402,537
[Sales].[Geography (Billing)]
	dx=174,113
	parent=Sales
	x=439,377
[Sales].[Geography (Shipping)]
	dx=189,113
	parent=Sales
	x=10,377
[Sales].[Origin Sales Channel]
	dx=184,93
	parent=Sales
	x=10,537
[Sales].[Submit Sales Channel]
	dx=190,93
	parent=Sales
	x=653,377
[Sales].[Agent]
	dx=125,113
	parent=Sales
	x=567,537
[Sales].[Time Interval]
	dx=136,93
	parent=Sales
	x=381,677
[Sales].[Submitted Site]
	dx=192,93
	parent=Sales
	x=190,1107
[Sales].[Origin Site]
	dx=156,93
	parent=Sales
	x=220,1137
[Sales].[Item Site]
	dx=139,93
	parent=Sales
	x=250,1167
[Sales]
	c=d8a77d
	dx=200,28
	expanded=f
	parent=Commerce
	view=0,0
	x=10,117
	zoom=1.000000
[Promotions].[Promotion Usage Measures]
	dx=182,89
	parent=Promotions
	x=255,819
[Promotions].[Promotion]
	dx=121,93
	parent=Promotions
	x=10,637
[Promotions].[Order]
	dx=128,113
	parent=Promotions
	x=10,748
[Promotions].[Date]
	dx=300,153
	parent=Promotions
	x=8,481
[Promotions].[Time]
	dx=111,113
	parent=Promotions
	x=309,482
[Promotions].[Catalog]
	dx=160,133
	parent=Promotions
	x=10,863
[Promotions].[Customer]
	dx=139,113
	parent=Promotions
	x=347,771
[Promotions].[Segment]
	dx=200,113
	parent=Promotions
	x=478,675
[Returns].[Submitted Site]
	dx=192,93
	parent=Returns
	x=41,1257
[Returns]
	c=89c6fd
	dx=200,28
	expanded=f
	parent=Commerce
	view=0,0
	x=903,117
	zoom=1.000000
[Commerce].[Time Interval]
	dx=136,93
	parent=Commerce
	x=778,1120
[Commerce]
	c=527ca5
	dx=1113,1760
	expanded=t
	parent=Dimensional View
	view=0,904
	x=10,57
	zoom=1.000000
[Dimensional View]
	c=568ef6
	dx=1133,1827
	expanded=t
	parent=ATG
	view=866,85
	x=11,44
	zoom=1.000000
[ATG]
	c=9bdfc4
	dx=6608,4801
	expanded=t
	parent=ATG
	view=159,2063
	x=10,57
	zoom=1.000000
[]
	NavigationRect=0,0,300,411
	Notation=4
	ShowGrid=1
	Snap=99
	font=Arial Narrow
	lod=33
	tc=323232
	view=0,0
	viewStyle=2
	zoom=1.000000
[Site Visits].[Site]
	dx=96,93
	parent=Site Visits
	x=70,44
[Site Visits].[Entry Site]
	dx=149,93
	parent=Site Visits
	x=100,74
[Site Visits].[Exit Site]
	dx=135,93
	parent=Site Visits
	x=130,104
[Site Visits].[Referring Site]
	dx=184,93
	parent=Site Visits
	x=160,134
[Site Visits]
	c=9bdfc4
	dx=200,28
	expanded=f
	parent=Commerce
	view=0,0
	x=10,1120
	zoom=1.000000
[Sales].[Line Item Measures]
	dx=174,109
	parent=Sales
	x=10,937
[Sales].[Order]
	dx=128,113
	parent=Sales
	x=234,537
[Sales].[Date]
	dx=300,153
	parent=Sales
	x=10,57
[Sales].[Time]
	dx=111,113
	parent=Sales
	x=557,677
[Sales].[Catalog]
	dx=160,133
	parent=Sales
	x=239,377
[Sales].[Search Term]
	dx=330,113
	parent=Sales
	x=350,57
[Sales].[Customer]
	dx=139,113
	parent=Sales
	x=347,319
[Sales].[Stimulus]
	dx=200,113
	parent=Sales
	x=10,237
[Sales].[Segment]
	dx=200,113
	parent=Sales
	x=250,237
[Sales].[Promotion]
	dx=200,113
	parent=Sales
	x=490,237
[Sales].[Local Currency]
	dx=150,93
	parent=Sales
	x=10,677
[Sales].[Gender]
	dx=103,93
	parent=Sales
	x=491,817
[Site Visits].[Date]
	dx=300,153
	parent=Site Visits
	x=10,117
[Site Visits].[Time]
	dx=111,113
	parent=Site Visits
	x=367,297
[Site Visits].[Visitor]
	dx=105,113
	parent=Site Visits
	x=171,396
[Site Visits].[Gender]
	dx=103,93
	parent=Site Visits
	x=325,437
[Site Visits].[Geography]
	dx=128,113
	parent=Site Visits
	x=590,117
[Site Visits].[Age Group]
	dx=123,93
	parent=Site Visits
	x=10,437
[Site Visits].[Marital Status]
	dx=141,93
	parent=Site Visits
	x=10,297
[Site Visits].[Stimulus]
	dx=200,113
	parent=Site Visits
	x=350,117
[Site Visits].[Time Interval]
	dx=136,93
	parent=Site Visits
	x=191,297
[ATGDW].[ARF_RETURN_ITEM]
	dx=222,229
	parent=ATGDW
	x=252,4450
[ATGDW].[ARF_RET_REASON_DISPOSITION]
	dx=263,129
	parent=ATGDW
	x=472,4450
[ATGDW].[ARF_IU_DIR_LVL]
	dx=163,109
	parent=ATGDW
	x=32,4506
[ATGDW].[ARF_IU_ORG]
	dx=139,189
	parent=ATGDW
	x=252,4506
[ATGDW].[ARF_IU_USER]
	dx=145,209
	parent=ATGDW
	x=472,4506
[ATGDW].[ARF_QUESTION]
	dx=208,149
	parent=ATGDW
	x=32,4562
[ATGDW].[ARF_TIME_INTERVAL]
	dx=190,169
	parent=ATGDW
	x=252,4562
[ATGDW].[ARF_PROMOTION_USAGE]
	dx=219,229
	parent=ATGDW
	x=472,4562
[ATGDW].[ARF_SITE]
	dx=256,229
	parent=ATGDW
	x=62,1959
[ATGDW]
	c=d8a77d
	dx=745,4801
	expanded=t
	parent=Database View
	view=0,3473
	x=10,57
	zoom=1.000000
[Database View]
	c=9bdfc4
	dx=765,4868
	expanded=t
	parent=ATG
	view=0,0
	x=11,1808
	zoom=1.000000
[Site Visit Facts].[Site Visit Facts]
	dx=217,229
	parent=Site Visit Facts
	x=1333,1566
[Site Visit Facts].[Site Visit]
	dx=338,89
	parent=Site Visit Facts
	x=292,1847
[Site Visit Facts].[Date]
	dx=195,229
	parent=Site Visit Facts
	x=389,313
[Site Visit Facts].[Time]
	dx=156,149
	parent=Site Visit Facts
	x=187,437
[Site Visit Facts].[Visitor]
	dx=281,229
	parent=Site Visit Facts
	x=210,1189
[Site Visit Facts].[Organization]
	dx=280,229
	parent=Site Visit Facts
	x=511,1189
[Site Visit Facts].[Demographic]
	dx=285,129
	parent=Site Visit Facts
	x=267,1658
[Site Visit Facts].[Gender]
	dx=231,89
	parent=Site Visit Facts
	x=10,1996
[Site Visit Facts].[Region]
	dx=229,149
	parent=Site Visit Facts
	x=572,1658
[Site Visit Facts].[Country]
	dx=237,169
	parent=Site Visit Facts
	x=10,1658
[Site Visit Facts].[Age Group]
	dx=262,129
	parent=Site Visit Facts
	x=10,1847
[Site Visit Facts].[Marital Status]
	dx=288,89
	parent=Site Visit Facts
	x=650,1847
[Site Visit Facts].[Stimulus Group]
	dx=306,189
	parent=Site Visit Facts
	x=783,1219
[Site Visit Facts].[Time Interval]
	dx=185,169
	parent=Site Visit Facts
	x=395,58
[Site Visit Facts].[Site]
	dx=180,449
	parent=Site Visit Facts
	x=10,1189
[Site Visit Facts].[Entry Site]
	dx=290,229
	parent=Site Visit Facts
	x=10,656
[Site Visit Facts].[Exit Site]
	dx=290,229
	parent=Site Visit Facts
	x=195,940
[Site Visit Facts].[Referring Site]
	dx=290,229
	parent=Site Visit Facts
	x=531,912
[Site Visit Facts]
	c=bf8cbc
	dx=200,28
	expanded=f
	parent=Commerce (Model)
	view=0,411
	x=3420,2433
	zoom=1.000000
[Sales Facts].[Line Item Facts]
	dx=219,229
	parent=Sales Facts
	x=940,1163
[Sales Facts].[Line Item]
	dx=115,129
	parent=Sales Facts
	x=10,307
[ATGDW].[ARF_STIMULUS]
	dx=164,229
	parent=ATGDW
	x=32,4282
[ATGDW].[ARF_SITE_VISIT]
	dx=157,229
	parent=ATGDW
	x=252,4282
[ATGDW].[ARF_SKU]
	dx=164,229
	parent=ATGDW
	x=472,4282
[ATGDW].[ARF_PRODUCT]
	dx=164,229
	parent=ATGDW
	x=32,4338
[ATGDW].[ARF_CATEGORY]
	dx=164,229
	parent=ATGDW
	x=252,4338
[ATGDW].[ARF_PROMOGRP]
	dx=165,109
	parent=ATGDW
	x=472,4338
[ATGDW].[ARF_PROMOTION]
	dx=168,229
	parent=ATGDW
	x=32,4394
[ATGDW].[ARF_PROMOGRP_MBRS]
	dx=209,69
	parent=ATGDW
	x=252,4394
[ATGDW].[ARF_LINE_ITEM]
	dx=254,229
	parent=ATGDW
	x=472,4394
[ATGDW].[ARF_SALES_CHANNEL]
	dx=200,149
	parent=ATGDW
	x=32,4450
[Commerce (Model)].[Date]
	dx=195,229
	parent=Commerce (Model)
	x=10,4384
[Commerce (Model)].[Time]
	dx=156,149
	parent=Commerce (Model)
	x=10,4633
[Commerce (Model)].[Site]
	dx=290,104
	parent=Commerce (Model)
	x=2866,2259
[Commerce (Model)].[Gender]
	dx=228,89
	parent=Commerce (Model)
	x=3208,1592
[Commerce (Model)].[Demographic]
	dx=181,129
	parent=Commerce (Model)
	x=2696,1472
[Commerce (Model)].[Marital Status]
	dx=275,89
	parent=Commerce (Model)
	x=3177,1355
[Commerce (Model)].[Age Group]
	dx=254,129
	parent=Commerce (Model)
	x=3050,1092
[Commerce (Model)].[Region (demographic)]
	dx=226,149
	parent=Commerce (Model)
	x=2830,940
[Commerce (Model)].[Country (demographic)]
	dx=243,169
	parent=Commerce (Model)
	x=2906,650
[Commerce (Model)].[User]
	dx=281,229
	parent=Commerce (Model)
	x=1994,913
[Commerce (Model)].[Organization]
	dx=200,229
	parent=Commerce (Model)
	x=2236,635
[Commerce (Model)].[Category]
	dx=330,229
	parent=Commerce (Model)
	x=1226,58
[Commerce (Model)].[Product]
	dx=319,229
	parent=Commerce (Model)
	x=1288,461
[Commerce (Model)].[Sku]
	dx=290,229
	parent=Commerce (Model)
	x=1356,848
[Commerce (Model)].[Local Currency]
	dx=241,129
	parent=Commerce (Model)
	x=916,1055
[Commerce (Model)].[Segment Cluster]
	dx=209,169
	parent=Commerce (Model)
	x=599,1302
[Commerce (Model)].[Agent]
	dx=146,169
	parent=Commerce (Model)
	x=396,1668
[Commerce (Model)].[Agent Organization]
	dx=233,169
	parent=Commerce (Model)
	x=110,1564
[Commerce (Model)].[Stimulus Group]
	dx=201,189
	parent=Commerce (Model)
	x=265,2082
[Commerce (Model)].[Region (billing)]
	dx=226,149
	parent=Commerce (Model)
	x=292,2536
[Commerce (Model)].[Country (billing)]
	dx=232,169
	parent=Commerce (Model)
	x=10,2599
[Commerce (Model)].[Sales Channel (origin)]
	dx=421,149
	parent=Commerce (Model)
	x=424,3003
[Commerce (Model)].[Sales Channel (submit)]
	dx=428,149
	parent=Commerce (Model)
	x=882,3385
[Commerce (Model)].[Site Visit Facts]
	dx=148,229
	parent=Commerce (Model)
	x=3213,2253
[Commerce (Model)].[Line Item Facts]
	dx=153,229
	parent=Commerce (Model)
	x=1610,2159
[Commerce (Model)].[Promotion Usage Facts]
	dx=197,29
	parent=Commerce (Model)
	x=491,529
[Commerce (Model)].[Return Item Facts]
	dx=164,229
	parent=Commerce (Model)
	x=1704,2203
[Commerce (Model)]
	c=99b2c7
	dx=6968,5195
	expanded=t
	parent=Model View
	view=1487,2020
	x=10,57
	zoom=1.000000
[Model View]
	c=89c6fd
	dx=6988,5262
	expanded=t
	parent=ATG
	view=1418,1249
	x=1731,44
	zoom=1.000000
[Site Visits].[Site Visit Measures]
	dx=172,89
	parent=Site Visits
	x=148,557
[Site Visits].[Site Visit]
	dx=112,93
	parent=Site Visits
	x=173,437
[ATGDW].[ARF_TIME_HOUR]
	dx=165,109
	parent=ATGDW
	x=472,3890
[ATGDW].[ARF_TIME_TOD]
	dx=154,149
	parent=ATGDW
	x=32,3946
[ATGDW].[ARF_CAL_QOY]
	dx=152,109
	parent=ATGDW
	x=252,3946
[ATGDW].[ARF_CAL_MOY]
	dx=152,109
	parent=ATGDW
	x=472,3946
[ATGDW].[ARF_CAL_DOW]
	dx=154,109
	parent=ATGDW
	x=32,4002
[ATGDW].[ARF_USER]
	dx=164,229
	parent=ATGDW
	x=252,4002
[ATGDW].[ARF_ORGANIZATION]
	dx=254,229
	parent=ATGDW
	x=414,3960
[ATGDW].[ARF_GENDER]
	dx=145,89
	parent=ATGDW
	x=472,4002
[ATGDW].[ARF_USER_GENDER]
	dx=186,89
	parent=ATGDW
	x=11,44
[ATGDW].[ARF_LANGUAGE]
	dx=163,169
	parent=ATGDW
	x=32,4058
[ATGDW].[ARF_USER_LANGUAGE]
	dx=204,169
	parent=ATGDW
	x=41,74
[ATGDW].[ARF_CURRENCY]
	dx=162,169
	parent=ATGDW
	x=252,4058
[ATGDW].[ARF_GEO_REGION]
	dx=175,189
	parent=ATGDW
	x=472,4058
[ATGDW].[ARF_USER_GEO_REGION]
	dx=216,189
	parent=ATGDW
	x=71,104
[ATGDW].[ARF_GEO_COUNTRY]
	dx=187,209
	parent=ATGDW
	x=32,4114
[ATGDW].[ARF_USER_GEO_COUNTRY]
	dx=229,209
	parent=ATGDW
	x=101,134
[ATGDW].[ARF_AGE_GROUP]
	dx=171,129
	parent=ATGDW
	x=252,4114
[ATGDW].[ARF_MARITAL_STATUS]
	dx=204,89
	parent=ATGDW
	x=472,4114
[ATGDW].[ARF_USER_MARITAL_STATUS]
	dx=245,89
	parent=ATGDW
	x=131,164
[ATGDW].[ARF_DEMOGRAPHIC]
	dx=186,129
	parent=ATGDW
	x=32,4170
[ATGDW].[ARF_SEGCLSTR]
	dx=159,109
	parent=ATGDW
	x=252,4170
[ATGDW].[ARF_SEGCLSTR_MBRS]
	dx=203,89
	parent=ATGDW
	x=472,4170
[ATGDW].[ARF_SEGMENT]
	dx=164,209
	parent=ATGDW
	x=32,4226
[ATGDW].[ARF_STIMGRP]
	dx=148,109
	parent=ATGDW
	x=252,4226
[ATGDW].[ARF_STIMGRP_MBRS]
	dx=192,69
	parent=ATGDW
	x=472,4226
[Sales Facts].[Order]
	dx=93,89
	parent=Sales Facts
	x=182,327
[Sales Facts].[Date]
	dx=195,229
	parent=Sales Facts
	x=10,58
[Sales Facts].[Time]
	dx=156,149
	parent=Sales Facts
	x=10,1770
[Sales Facts].[Category]
	dx=330,229
	parent=Sales Facts
	x=10,456
[Sales Facts].[Product]
	dx=319,229
	parent=Sales Facts
	x=360,456
[Sales Facts].[Sku]
	dx=290,229
	parent=Sales Facts
	x=10,705
[Sales Facts].[Search Term]
	dx=235,109
	parent=Sales Facts
	x=530,1601
[Sales Facts].[Customer]
	dx=281,229
	parent=Sales Facts
	x=630,705
[Sales Facts].[Organization]
	dx=280,229
	parent=Sales Facts
	x=931,705
[Sales Facts].[Stimulus Group]
	dx=333,189
	parent=Sales Facts
	x=458,954
[Sales Facts].[Segment Cluster]
	dx=209,169
	parent=Sales Facts
	x=1133,1412
[Sales Facts].[Promotion Group]
	dx=234,229
	parent=Sales Facts
	x=367,1163
[Sales Facts].[Local Currency]
	dx=301,129
	parent=Sales Facts
	x=573,1412
[Sales Facts].[Demographic]
	dx=181,129
	parent=Sales Facts
	x=1080,1601
[Sales Facts].[Gender]
	dx=228,89
	parent=Sales Facts
	x=186,1770
[Sales Facts].[Age Group]
	dx=254,129
	parent=Sales Facts
	x=256,1601
[Sales Facts].[Marital Status]
	dx=275,89
	parent=Sales Facts
	x=785,1601
[Sales Facts].[Region]
	dx=226,149
	parent=Sales Facts
	x=10,1601
[Sales Facts].[Country]
	dx=232,169
	parent=Sales Facts
	x=321,1412
[Sales Facts].[Billing Region]
	dx=291,149
	parent=Sales Facts
	x=10,1412
[Sales Facts].[Billing Country]
	dx=299,169
	parent=Sales Facts
	x=621,1163
[Sales Facts].[Shipping Region]
	dx=159,149
	parent=Sales Facts
	x=506,68
[Sales Facts].[Shipping Country]
	dx=163,169
	parent=Sales Facts
	x=740,58
[Sales Facts].[Origin Sales Channel]
	dx=421,149
	parent=Sales Facts
	x=811,954
[Sales Facts].[Submit Sales Channel]
	dx=428,149
	parent=Sales Facts
	x=10,954
[Sales Facts].[Agent]
	dx=219,169
	parent=Sales Facts
	x=894,1412
[Sales Facts].[Agent Organization]
	dx=337,169
	parent=Sales Facts
	x=10,1163
[Sales Facts].[Time Interval]
	dx=185,169
	parent=Sales Facts
	x=301,88
[Sales Facts].[Submitted Site]
	dx=290,229
	parent=Sales Facts
	x=320,705
[Sales Facts].[Origin Site]
	dx=290,229
	parent=Sales Facts
	x=699,456
[Sales Facts].[Item Site]
	dx=290,229
	parent=Sales Facts
	x=1009,456
[Sales Facts]
	c=758698
	dx=1352,1929
	expanded=t
	parent=Commerce (Model)
	view=0,67
	x=1707,2435
	zoom=1.000000
[Promotion Facts].[Promotion Usage Facts]
	dx=267,229
	parent=Promotion Facts
	x=949,807
[Promotion Facts].[Promotion]
	dx=234,229
	parent=Promotion Facts
	x=3248,1228
[Promotion Facts].[Order]
	dx=93,89
	parent=Promotion Facts
	x=2834,1561
[Promotion Facts].[Date]
	dx=195,229
	parent=Promotion Facts
	x=2960,1541
[Promotion Facts].[Time]
	dx=156,149
	parent=Promotion Facts
	x=3185,1498
[Promotion Facts].[Category]
	dx=330,229
	parent=Promotion Facts
	x=2472,2045
[Promotion Facts].[Product]
	dx=319,229
	parent=Promotion Facts
	x=2822,2045
[Promotion Facts].[Sku]
	dx=290,229
	parent=Promotion Facts
	x=3161,2045
[Promotion Facts].[Customer]
	dx=281,229
	parent=Promotion Facts
	x=2472,2294
[Promotion Facts].[Organization]
	dx=200,229
	parent=Promotion Facts
	x=2773,2294
[Promotion Facts].[Segment Cluster]
	dx=209,169
	parent=Promotion Facts
	x=2472,2543
[Promotion Facts].[Local Currency]
	dx=241,129
	parent=Promotion Facts
	x=3221,2543
[Promotion Facts].[Demographic]
	dx=181,129
	parent=Promotion Facts
	x=3111,2732
[Promotion Facts].[Gender]
	dx=228,89
	parent=Promotion Facts
	x=2472,2921
[Promotion Facts].[Age Group]
	dx=254,129
	parent=Promotion Facts
	x=2947,2543
[Promotion Facts].[Marital Status]
	dx=275,89
	parent=Promotion Facts
	x=2816,2732
[Promotion Facts].[Region]
	dx=226,149
	parent=Promotion Facts
	x=2701,2543
[Promotion Facts].[Country]
	dx=232,169
	parent=Promotion Facts
	x=3246,2294
[Promotion Facts].[Billing Region]
	dx=319,149
	parent=Promotion Facts
	x=3245,2018
[Promotion Facts].[Billing Country]
	dx=327,169
	parent=Promotion Facts
	x=3275,2048
[Promotion Facts].[Origin Sales Channel]
	dx=421,149
	parent=Promotion Facts
	x=11,44
[Promotion Facts].[Submit Sales Channel]
	dx=428,149
	parent=Promotion Facts
	x=41,74
[Promotion Facts].[Agent]
	dx=146,169
	parent=Promotion Facts
	x=2650,2732
[Promotion Facts].[Agent Organization]
	dx=233,169
	parent=Promotion Facts
	x=2993,2294
[Promotion Facts].[Time Interval]
	dx=185,169
	parent=Promotion Facts
	x=2970,1856
[Promotion Facts].[Submitted Site]
	dx=290,229
	parent=Promotion Facts
	x=3471,2045
[Promotion Facts]
	c=73d3ac
	dx=3771,3020
	expanded=t
	parent=Commerce (Model)
	view=98,990
	x=3187,2165
	zoom=1.000000
[Return Facts].[Return Item Facts]
	dx=234,229
	parent=Return Facts
	x=621,327
[Return Facts].[Return Date]
	dx=195,229
	parent=Return Facts
	x=10,576
[Return Facts].[Return Time]
	dx=170,149
	parent=Return Facts
	x=288,825
[Return Facts].[Category]
	dx=330,229
	parent=Return Facts
	x=10,78
[Return Facts].[Product]
	dx=319,229
	parent=Return Facts
	x=360,78
[Return Facts].[Sku]
	dx=290,229
	parent=Return Facts
	x=699,78
[Return Facts].[Customer]
	dx=281,229
	parent=Return Facts
	x=320,327
[Return Facts].[Organization]
	dx=200,229
	parent=Return Facts
	x=875,327
[Return Facts].[Local Currency]
	dx=241,129
	parent=Return Facts
	x=790,576
[Return Facts].[Return Reason]
	dx=258,109
	parent=Return Facts
	x=10,825
[Return Facts].[Return Sales Channel]
	dx=292,149
	parent=Return Facts
	x=225,576
[Return Facts].[Agent]
	dx=146,169
	parent=Return Facts
	x=478,825
[Return Facts].[Agent Organization]
	dx=233,169
	parent=Return Facts
	x=537,576
[Return Facts].[Time Interval]
	dx=185,29
	parent=Return Facts
	x=644,825
[Return Facts].[Item Site]
	dx=290,229
	parent=Return Facts
	x=1009,78
[Return Facts].[Submitted Site]
	dx=290,229
	parent=Return Facts
	x=10,327
[Return Facts]
	c=99f7ff
	dx=200,28
	expanded=f
	parent=Commerce (Model)
	view=0,63
	x=1965,677
	zoom=1.000000
[Commerce (Model)].[Time Interval]
	dx=185,169
	parent=Commerce (Model)
	x=225,4384
[ATGDW].[ARF_TIME_DAY]
	dx=154,189
	parent=ATGDW
	x=358,2152
[ATGDW].[ARF_TIME_MONTH]
	dx=174,149
	parent=ATGDW
	x=388,2182
[ATGDW].[ARF_TIME_QTR]
	dx=154,129
	parent=ATGDW
	x=418,2212
[ATGDW].[ARF_TIME_YEAR]
	dx=163,89
	parent=ATGDW
	x=448,2242
[ATGDW].[ARF_TIME_WEEKYEAR]
	dx=200,89
	parent=ATGDW
	x=478,2272
[ATGDW].[ARF_TIME_WEEK]
	dx=165,109
	parent=ATGDW
	x=538,2332
]]></property></object></namespace></bmtcustomdata>
<!-- @version $Id: //product/DCS/version/10.0.3/DW/cpf/customdata.xml#2 $$Change: 651448 $-->
